sentinel/__init__.py
sentinel/cli.py
sentinel/rules.py
sentinel/sentinel.py
sentinel/settings.py
sentinel/database/__init__.py
sentinel/database/service_manager.py
sentinel/database/services/__init__.py
sentinel/database/services/base.py
sentinel/database/services/postgres.py
sentinel/database/services/sqlite3.py
sentinel/output/__init__.py
sentinel/output/mqtt.py
sentinel/output/pushbullet.py
sentinel/tests/__init__.py
sentinel/tests/unit_tests/__init__.py
sentinel/tests/unit_tests/db_services/__init__.py
sentinel/tests/unit_tests/db_services/test_sqlite3.py
sentinel/tests/unit_tests/output/__init__.py
sentinel/tests/unit_tests/output/test_output.py
sentinel/tests/unit_tests/output/test_pushbullet.py
sentinel/tests/unit_tests/rules/__init__.py
sentinel/tests/unit_tests/rules/test_rule_object.py
sentinel/watcher/__init__.py
sentinel/watcher/resources.py
sentinel/watcher/watcher.py
mqtt_sentinel-0.8.2.dist-info/METADATA
mqtt_sentinel-0.8.2.dist-info/WHEEL
mqtt_sentinel-0.8.2.dist-info/entry_points.txt
mqtt_sentinel-0.8.2.dist-info/top_level.txt
mqtt_sentinel-0.8.2.dist-info/RECORD
