Metadata-Version: 2.1
Name: mqtt-sentinel
Version: 0.8.2
Summary: Integration between MQTT and custom notification services.
Home-page: https://github.com/caiovictormc/mqtt-sentinel
Author: caiovictormc
Author-email: caiovictormc@gmail.com
License: MIT
Platform: UNKNOWN
Classifier: Development Status :: 4 - Beta
Classifier: License :: OSI Approved :: MIT License
Classifier: Programming Language :: Python :: 3.7
Classifier: Topic :: System :: Networking :: Monitoring
Requires-Dist: paho-mqtt (==1.4.0)
Requires-Dist: PyInquirer (==1.0.3)
Requires-Dist: prompt-toolkit (==1.0.14)
Requires-Dist: click (==7.0)
Requires-Dist: colorama (==0.4.1)
Requires-Dist: requests (==2.21.0)
